{"id":7653207,"name":"Aqua Jet","type":"Spell Card","frameType":"spell","desc":"Target 1 face-up Fish, Sea Serpent, or Aqua-Type monster you control; it gains 1000 ATK.","race":"Normal","card_sets":[{"set_name":"Generation Force","set_code":"GENF-EN048","set_rarity":"Common","set_rarity_code":"(C)","set_price":"1.76"},{"set_name":"Realm of the Sea Emperor Structure Deck","set_code":"SDRE-EN027","set_rarity":"Common","set_rarity_code":"(C)","set_price":"1.26"}],"card_images":[{"id":7653207,"image_url":"https://images.ygoprodeck.com/images/cards/7653207.jpg","image_url_small":"https://images.ygoprodeck.com/images/cards_small/7653207.jpg","image_url_cropped":"https://images.ygoprodeck.com/images/cards_cropped/7653207.jpg"}],"card_prices":[{"cardmarket_price":"0.15","tcgplayer_price":"0.24","ebay_price":"1.50","amazon_price":"0.20","coolstuffinc_price":"0.25"}]}